throwaway_vpn/__init__.py
throwaway_vpn/user_data.py
throwaway_vpn/vpn.py
throwaway_vpn-0.0.6.dist-info/AUTHORS.rst
throwaway_vpn-0.0.6.dist-info/LICENSE
throwaway_vpn-0.0.6.dist-info/METADATA
throwaway_vpn-0.0.6.dist-info/WHEEL
throwaway_vpn-0.0.6.dist-info/entry_points.txt
throwaway_vpn-0.0.6.dist-info/top_level.txt
throwaway_vpn-0.0.6.dist-info/RECORD
